setup.py
ImageQualityChecker.egg-info/PKG-INFO
ImageQualityChecker.egg-info/SOURCES.txt
ImageQualityChecker.egg-info/dependency_links.txt
ImageQualityChecker.egg-info/requires.txt
ImageQualityChecker.egg-info/top_level.txt
checker/QualityChecker_ONNX.py
checker/__init__.py
checker/efficientnet_b3_qualitycheck.onnx
checker/test.py